fast_engset/__init__.py
fast_engset/_fast_engset.py
fast_engset-3.0.1.dist-info/LICENSE
fast_engset-3.0.1.dist-info/METADATA
fast_engset-3.0.1.dist-info/WHEEL
fast_engset-3.0.1.dist-info/top_level.txt
fast_engset-3.0.1.dist-info/RECORD
