Metadata-Version: 2.1
Name: fast-engset
Version: 3.0.1
Summary: Fast and accurate routines to compute various quantities in the Engset model.
Home-page: https://github.com/parsiad/fast-engset
Author: Parsiad Azimzadeh, Tommy Carpenter
Author-email: parsiad.azimzadeh@gmail.com
License: MIT
Platform: UNKNOWN
Requires-Dist: numpy
Requires-Dist: enum ; python_version < "3"
Requires-Dist: numba ; python_version >= "3"
